oscar_test0629/__init__.py
oscar_test0629/data.py
oscar_test0629-0.1.1.dist-info/METADATA
oscar_test0629-0.1.1.dist-info/WHEEL
oscar_test0629-0.1.1.dist-info/top_level.txt
oscar_test0629-0.1.1.dist-info/RECORD
