Metadata-Version: 2.1
Name: oscar-test0629
Version: 0.1.1
Summary: For testing.
Home-page: https://github.com/oscar-finance/oscar_test0629
Author: Oscar
Author-email: yihongcurry30@gmail.com
License: MIT
Platform: UNKNOWN
Classifier: License :: OSI Approved :: MIT License
Classifier: Programming Language :: Python
Classifier: Programming Language :: Python :: 3
Classifier: Programming Language :: Python :: 3.6
Classifier: Programming Language :: Python :: Implementation :: CPython
Classifier: Programming Language :: Python :: Implementation :: PyPy
Requires-Python: >=3.6.0
Requires-Dist: ipykernel (==5.5.3)
Requires-Dist: requests (==2.22.0)
Requires-Dist: beautifulsoup4 (==4.9.3)
Requires-Dist: selenium (==3.141.0)
Requires-Dist: ipywidgets (==7.4.2)
Requires-Dist: tqdm (==4.31.1)
Requires-Dist: seaborn (==0.11.1)
Requires-Dist: plotly (==4.14.3)
Requires-Dist: pyecharts (==1.7.1)
Requires-Dist: yfinance (==0.1.59)
Requires-Dist: fugle-realtime (==0.2.9)
Requires-Dist: tensorflow (==1.14.0)
Requires-Dist: scikit-learn (==0.24.2)
Requires-Dist: lightgbm (==3.1.1)
Requires-Dist: xgboost (==1.4.2)
Requires-Dist: keras (==2.2.4)
Requires-Dist: pandas (==1.1.3)
Requires-Dist: numpy (==1.20.0)
Requires-Dist: talib-binary (==0.4.19)
